pygame_networking/__init__.py
pygame_networking-0.0.1.dist-info/LICENSE
pygame_networking-0.0.1.dist-info/METADATA
pygame_networking-0.0.1.dist-info/WHEEL
pygame_networking-0.0.1.dist-info/top_level.txt
pygame_networking-0.0.1.dist-info/RECORD
