Metadata-Version: 2.1
Name: pygame_networking
Version: 0.0.1
Summary: Python networking library perfect for use with pygame!
Home-page: https://github.com/StarLitDragon404/pygame_networking
Author: Maxim
Author-email: "maximko.ca@gmail.com"
Project-URL: Bug Tracker, https://github.com/StarLitDragon404/pygame_networking/issues
Classifier: Programming Language :: Python :: 3
Classifier: License :: OSI Approved :: MIT License
Classifier: Operating System :: OS Independent
Requires-Python: >=3.9
License-File: LICENSE
